mcp_server_baidu_maps/__init__.py
mcp_server_baidu_maps/__main__.py
mcp_server_baidu_maps/map.py
mcp_server_baidu_maps-0.2.3.dist-info/licenses/LICENSE
mcp_server_baidu_maps-0.2.3.dist-info/METADATA
mcp_server_baidu_maps-0.2.3.dist-info/WHEEL
mcp_server_baidu_maps-0.2.3.dist-info/entry_points.txt
mcp_server_baidu_maps-0.2.3.dist-info/top_level.txt
mcp_server_baidu_maps-0.2.3.dist-info/RECORD
